src/gitro.py
gitro-1.1.0.dist-info/METADATA
gitro-1.1.0.dist-info/WHEEL
gitro-1.1.0.dist-info/entry_points.txt
gitro-1.1.0.dist-info/licenses/LICENSE
gitro-1.1.0.dist-info/RECORD
