Metadata-Version: 2.4
Name: gitro
Version: 1.1.0
Summary: Open the current repository on your browser
Project-URL: homepage, https://github.com/nunokaeru/gitro
Project-URL: repository, https://github.com/nunokaeru/gitro
Author-email: Nuno Mendes <nunoricardomendes@gmail.com>
License: MIT License
License-File: LICENSE
Classifier: License :: OSI Approved :: MIT License
Classifier: Operating System :: OS Independent
Classifier: Programming Language :: Python
Classifier: Programming Language :: Python :: 3
Classifier: Programming Language :: Python :: 3 :: Only
Classifier: Programming Language :: Python :: 3.11
Classifier: Programming Language :: Python :: 3.12
Classifier: Programming Language :: Python :: 3.13
Classifier: Programming Language :: Python :: 3.14
Requires-Python: >=3.11
